Metadata-Version: 2.1
Name: ipynb2catsoop
Version: 0.0.1
Summary: Converter from ipython / jupyter notebook to catsoop
Home-page: https://github.com/ichuang/ipynb2catsoop
Author: I. Chuang
Author-email: ichuang@mit.edu
License: LICENSE
Platform: UNKNOWN
